{
  "project_info": {
    "project_number": "991533143014",
    "firebase_url": "https://radio-corredor-ifac.firebaseio.com",
    "project_id": "radio-corredor-ifac",
    "storage_bucket": "radio-corredor-ifac.appspot.com"
  },
  "client": [
    {
      "client_info": {
        "mobilesdk_app_id": "1:991533143014:android:fdc4b28aea27b8ee417c27",
        "android_client_info": {
          "package_name": "com.radiowebapplication"
        }
      },
      "oauth_client": [
        {
          "client_id": "991533143014-2dptu5g99i8fa3poafh5avikkisjbir7.apps.googleusercontent.com",
          "client_type": 1,
          "android_info": {
            "package_name": "com.radiowebapplication",
            "certificate_hash": "2fd53fc2a5aa3a5895625ea813f531e9fff9bb05"
          }
        },
        {
          "client_id": "991533143014-vkbfudrbkchtjclih1fi57k6orrkk5q0.apps.googleusercontent.com",
          "client_type": 3
        }
      ],
      "api_key": [
        {
          "current_key": "AIzaSyCjr2BiatBy9NhR-syeKu_PjZBC0aVsk9A"
        }
      ],
      "services": {
        "appinvite_service": {
          "other_platform_oauth_client": [
            {
              "client_id": "991533143014-vkbfudrbkchtjclih1fi57k6orrkk5q0.apps.googleusercontent.com",
              "client_type": 3
            }
          ]
        }
      }
    }
  ],
  "configuration_version": "1"
}